odoo/addons/ssi_mrp_production/README.rst
odoo/addons/ssi_mrp_production/__init__.py
odoo/addons/ssi_mrp_production/__manifest__.py
odoo/addons/ssi_mrp_production/hooks.py
odoo/addons/ssi_mrp_production/data/mrp_production_type.xml
odoo/addons/ssi_mrp_production/data/policy_template_data.xml
odoo/addons/ssi_mrp_production/migrations/14.0.2.0.0/post-migration.py
odoo/addons/ssi_mrp_production/models/__init__.py
odoo/addons/ssi_mrp_production/models/mrp_production.py
odoo/addons/ssi_mrp_production/models/mrp_production_type.py
odoo/addons/ssi_mrp_production/security/ir.model.access.csv
odoo/addons/ssi_mrp_production/security/ir_module_category_data.xml
odoo/addons/ssi_mrp_production/security/res_group_data.xml
odoo/addons/ssi_mrp_production/static/description/icon.png
odoo/addons/ssi_mrp_production/views/mrp_bom_views.xml
odoo/addons/ssi_mrp_production/views/mrp_production_type_views.xml
odoo/addons/ssi_mrp_production/views/mrp_production_views.xml
odoo/addons/ssi_mrp_production/views/mrp_unbuild_views.xml
odoo/addons/ssi_mrp_production/views/product_product_views.xml
odoo/addons/ssi_mrp_production/views/product_template_views.xml
odoo/addons/ssi_mrp_production/views/stock_production_lot_views.xml
odoo/addons/ssi_mrp_production/views/stock_scheduler_compute_views.xml
odoo/addons/ssi_mrp_production/views/stock_scrap_views.xml
odoo14_addon_ssi_mrp_production-14.0.2.2.0.dist-info/METADATA
odoo14_addon_ssi_mrp_production-14.0.2.2.0.dist-info/WHEEL
odoo14_addon_ssi_mrp_production-14.0.2.2.0.dist-info/top_level.txt
odoo14_addon_ssi_mrp_production-14.0.2.2.0.dist-info/RECORD
