Metadata-Version: 2.1
Name: odoo14-addon-ssi-mrp-production
Version: 14.0.2.2.0
Summary: MRP Production
Home-page: https://simetri-sinergi.id
Author: OpenSynergy Indonesia, PT. Simetri Sinergi Indonesia
License: AGPL-3
Platform: UNKNOWN
Classifier: Programming Language :: Python
Classifier: Framework :: Odoo
Classifier: Framework :: Odoo :: 14.0
Classifier: License :: OSI Approved :: GNU Affero General Public License v3
Requires-Python: >=3.6
Requires-Dist: odoo14-addon-ssi-master-data-mixin
Requires-Dist: odoo14-addon-ssi-policy-mixin
Requires-Dist: odoo14-addon-ssi-stock-account
Requires-Dist: odoo14-addon-stock-move-backdating
Requires-Dist: odoo <14.1dev,>=14.0a
